pyhstr/__init__.py
pyhstr/__main__.py
pyhstr/application.py
pyhstr/user_interface.py
pyhstr/utilities.py
tests/__init__.py
tests/favorites/fake_bpython_favorites
tests/favorites/fake_ipython_favorites
tests/favorites/fake_python_favorites
tests/fixtures.py
tests/history/fake_bpython_history
tests/history/fake_ipython_history
tests/history/fake_python_history
tests/run
tests/test_app.py
tests/test_ui.py
tests/test_utilities.py
pyhstr-0.5.2.dist-info/LICENSE
pyhstr-0.5.2.dist-info/WHEEL
pyhstr-0.5.2.dist-info/METADATA
pyhstr-0.5.2.dist-info/RECORD
