Metadata-Version: 2.1
Name: pyhstr
Version: 0.5.2
Summary: History suggest box for the standard Python shell, IPython, and bpython
License: MIT
Author: adder46
Author-email: dedmauz69@gmail.com
Requires-Python: >=3.7,<4.0
Classifier: License :: OSI Approved :: MIT License
Classifier: Programming Language :: Python :: 3
Classifier: Programming Language :: Python :: 3.7
Classifier: Programming Language :: Python :: 3.8
Classifier: Programming Language :: Python :: 3.9
